LICENSE.txt
MANIFEST.in
README.rst
demo_ezmarkdown.ipynb
setup.cfg
setup.py
ezmarkdown/__init__.py
ezmarkdown/_generate_html.py
ezmarkdown/_md_to_html.py
ezmarkdown/template.py
ezmarkdown.egg-info/PKG-INFO
ezmarkdown.egg-info/SOURCES.txt
ezmarkdown.egg-info/dependency_links.txt
ezmarkdown.egg-info/top_level.txt
ezmarkdown/template/html_input.tpl
ezmarkdown/template/html_input_output.tpl
ezmarkdown/template/html_input_toggle_output.tpl
ezmarkdown/template/html_output.tpl
ezmarkdown/template/html_output_toggle_input.tpl