Metadata-Version: 1.1
Name: ezmarkdown
Version: 0.1.2
Summary: easy markdown: Write markdown in IPython notebook and generate standalone HTML file from it, picking the cells to output
Home-page: https://github.com/oscar6echo/ezmarkdown
Author: oscar6echo
Author-email: olivier.borderies@gmail.com
License: MIT
Download-URL: https://github.com/oscar6echo/ezmarkdown/tarball/0.1.2
Keywords: markdown,export,notebook,HTML
Platform: UNKNOWN
Classifier: Development Status :: 4 - Beta
Classifier: License :: OSI Approved :: MIT License
Classifier: Programming Language :: Python :: 2.7
